Metadata-Version: 2.1
Name: Parneet26-topsispkg
Version: 1.0.4
Summary: A package that calculates Topsis Score and Rank them accordingly
Home-page: https://github.com/Parneet-26/Topsis-python
Author: Parneet Kaur Rakhra
Author-email: prakhra_be19@thapar.edu
License: MIT
Platform: UNKNOWN
Classifier: Programming Language :: Python :: 3
Classifier: License :: OSI Approved :: MIT License
Classifier: Operating System :: OS Independent
